lingam/__init__.py
lingam/base.py
lingam/bootstrap.py
lingam/bottom_up_parce_lingam.py
lingam/camuv.py
lingam/causal_based_simulator.py
lingam/causal_effect.py
lingam/direct_lingam.py
lingam/group_direct_lingam.py
lingam/group_lingam.py
lingam/high_dim_direct_lingam.py
lingam/hsic.py
lingam/ica_lingam.py
lingam/lim.py
lingam/lina.py
lingam/longitudinal_lingam.py
lingam/multi_group_camuv.py
lingam/multi_group_direct_lingam.py
lingam/multi_group_rcd.py
lingam/rcd.py
lingam/resit.py
lingam/var_lingam.py
lingam/varma_lingam.py
lingam/experimental/__init__.py
lingam/experimental/cdg.py
lingam/experimental/oct.py
lingam/tools/__init__.py
lingam/utils/__init__.py
lingam/utils/_common_edge.py
lingam/utils/_f_correlation.py
lingam/utils/_rcd.py
lingam/utils/_visualize_nonlinear_causal_effect.py
lingam-1.11.0.dist-info/licenses/LICENSE
lingam-1.11.0.dist-info/METADATA
lingam-1.11.0.dist-info/WHEEL
lingam-1.11.0.dist-info/top_level.txt
lingam-1.11.0.dist-info/RECORD
