Metadata-Version: 2.4
Name: lingam
Version: 1.11.0
Summary: LiNGAM Python Package
Home-page: https://github.com/cdt15/lingam
Author: T.Ikeuchi, G.Haraoka, M.Ide, Y.Zeng, T.N.Maeda, W.Kurebayashi, S.Shimizu
Classifier: Programming Language :: Python :: 3
Classifier: License :: OSI Approved :: MIT License
Classifier: Operating System :: OS Independent
Requires-Python: >=3.9
License-File: LICENSE
Requires-Dist: numpy
Requires-Dist: scipy
Requires-Dist: scikit-learn
Requires-Dist: graphviz
Requires-Dist: statsmodels
Requires-Dist: networkx
Requires-Dist: pandas
Requires-Dist: pygam
Requires-Dist: matplotlib
Requires-Dist: psy
Requires-Dist: semopy
Dynamic: author
Dynamic: classifier
Dynamic: description
Dynamic: description-content-type
Dynamic: home-page
Dynamic: license-file
Dynamic: requires-dist
Dynamic: requires-python
Dynamic: summary
